dyson_equalizer/__init__.py
dyson_equalizer/_version.py
dyson_equalizer/algorithm.py
dyson_equalizer/dyson_equalizer.py
dyson_equalizer/examples.py
dyson_equalizer/plots.py
dyson_equalizer/validation.py
dyson_equalizer-0.1.8.dist-info/licenses/LICENSE
dyson_equalizer-0.1.8.dist-info/WHEEL
dyson_equalizer-0.1.8.dist-info/METADATA
dyson_equalizer-0.1.8.dist-info/RECORD
