Metadata-Version: 2.4
Name: dyson-equalizer
Version: 0.1.8
Summary: Computes the Dyson Equalizer and related low rank approximation of the input data
Keywords: Dyson Equalizer,low rank approximation
Author-email: Boris Landa <boris.landa@yale.edu>, Francesco Strino <francesco.strino@pcmgf.com>, Yuval Kluger <yuval.kluger@yale.edu>
Maintainer-email: Francesco Strino <francesco.strino@pcmgf.com>
Requires-Python: >=3.10
Classifier: Development Status :: 4 - Beta
Classifier: Programming Language :: Python
Classifier: License :: OSI Approved :: BSD License
Classifier: Intended Audience :: Science/Research
License-File: LICENSE
Requires-Dist: matplotlib>=3.6
Requires-Dist: numpy>=1.25
Requires-Dist: pytest ; extra == "dev"
Requires-Dist: flit_core ; extra == "dev"
Requires-Dist: flit_scm ; extra == "dev"
Project-URL: Bug Tracker, https://github.com/KlugerLab/DysonEqualizer/issues
Project-URL: Documentation, https://github.com/KlugerLab/DysonEqualizer.git
Project-URL: Repository, https://github.com/KlugerLab/DysonEqualizer.git
Provides-Extra: dev
